chatterstack/__init__.py
chatterstack/chatterstack.py
chatterstack/chatterstackadvanced.py
chatterstack/commands.py
chatterstack-2.0.1.dist-info/METADATA
chatterstack-2.0.1.dist-info/WHEEL
chatterstack-2.0.1.dist-info/top_level.txt
chatterstack-2.0.1.dist-info/RECORD
